windowsxplll/__init__.py
windowsxplll/projects/__init__.py
windowsxplll/projects/config.py
windowsxplll/projects/dimension_reduction.py
windowsxplll/projects/main_stand.py
windowsxplll/projects/predict.py
windowsxplll/root/TimeSeriesFactor.py
windowsxplll/root/__init__.py
windowsxplll/root/model_automl_with_auto_dt.py
windowsxplll/root/readme.py
windowsxplll/root/requirements.py
windowsxplll/src/__init__.py
windowsxplll/src/cat_search_space.py
windowsxplll/src/config.py
windowsxplll/src/evaluation.py
windowsxplll/src/feature_engineering.py
windowsxplll/src/feature_processor.py
windowsxplll/src/lgb_search_space.py
windowsxplll/src/model_automl.py
windowsxplll/src/model_ensemble.py
windowsxplll/src/model_stacking.py
windowsxplll/src/model_tuning.py
windowsxplll/src/xgb_search_space.py
windowsxplll-0.1.0.dist-info/METADATA
windowsxplll-0.1.0.dist-info/WHEEL
windowsxplll-0.1.0.dist-info/entry_points.txt
windowsxplll-0.1.0.dist-info/top_level.txt
windowsxplll-0.1.0.dist-info/RECORD
